lospec2css.py
lospec2css-0.1.0.dist-info/LICENSE
lospec2css-0.1.0.dist-info/WHEEL
lospec2css-0.1.0.dist-info/METADATA
lospec2css-0.1.0.dist-info/RECORD
